jicastringutils/__init__.py
jicastringutils/process.py
jicastringutils-1.2.0.dist-info/LICENSE.txt
jicastringutils-1.2.0.dist-info/METADATA
jicastringutils-1.2.0.dist-info/WHEEL
jicastringutils-1.2.0.dist-info/entry_points.txt
jicastringutils-1.2.0.dist-info/top_level.txt
jicastringutils-1.2.0.dist-info/RECORD
